taskcluster_inspect/__init__.py
taskcluster_inspect/console/application.py
taskcluster_inspect/console/commands/pool.py
taskcluster_inspect/console/commands/worker_manager.py
taskcluster_inspect/pool.py
taskcluster_inspect/task.py
taskcluster_inspect-0.3.0.dist-info/entry_points.txt
taskcluster_inspect-0.3.0.dist-info/WHEEL
taskcluster_inspect-0.3.0.dist-info/METADATA
taskcluster_inspect-0.3.0.dist-info/RECORD
