Metadata-Version: 2.1
Name: taskcluster-inspect
Version: 0.3.0
Summary: A simple command line tool for inspecting Taskcluster state.
License: MPL-2.0
Author: Andrew Halberstadt
Author-email: ahal@pm.me
Requires-Python: >=3.7,<4.0
Classifier: License :: OSI Approved
Classifier: Programming Language :: Python :: 3
Classifier: Programming Language :: Python :: 3.10
Classifier: Programming Language :: Python :: 3.7
Classifier: Programming Language :: Python :: 3.8
Classifier: Programming Language :: Python :: 3.9
Requires-Dist: cleo (>=0.8.1,<0.9.0)
Requires-Dist: petl (>=1.7.9,<2.0.0)
Requires-Dist: tabulate (>=0.8.9,<0.9.0)
Requires-Dist: taskcluster (>=44.13.6,<45.0.0)
